weatherfrcst/__init__.py
weatherfrcst/forecast.py
weatherfrcst-0.0.1.dist-info/LICENSE
weatherfrcst-0.0.1.dist-info/METADATA
weatherfrcst-0.0.1.dist-info/WHEEL
weatherfrcst-0.0.1.dist-info/top_level.txt
weatherfrcst-0.0.1.dist-info/RECORD
