Metadata-Version: 2.1
Name: weatherfrcst
Version: 0.0.1
Summary: Location based weather forecast package
Home-page: https://github.com/RishiKr3101/weather-forecast.git
Author: Rishi
Author-email: rishikrofficial@gmail.com
License: MIT
Platform: UNKNOWN
Requires-Dist: geopy
